{
  "title": "\u003Cspan class=\u0022highlight\u0022\u003EASP.NET\u003C/span\u003E core and React.js",
  "createdOn": "2024-03-04T16:45:41\u002B00:00",
  "type": 2,
  "ciphertext": "~017b4adef8bf55b5f9",
  "description": "Looking for Full-stack developer with \u003Cspan class=\u0022highlight\u0022\u003EASP.NET\u003C/span\u003E \u002B React.js. Please write me \u0026quot;coca-cola\u0026quot; at the first line of your cover.\n\nCheers,\nChris",
  "category2": null,
  "subcategory2": null,
  "duration": "3 to 6 months",
  "shortDuration": "3-6 months",
  "durationLabel": "3 to 6 months",
  "engagement": "30\u002B hrs/week",
  "shortEngagement": "30\u002B",
  "amount": {
    "currencyCode": "USD",
    "amount": 0
  },
  "recno": 1011749802,
  "uid": "1764693706390851584",
  "client": {
    "paymentVerificationStatus": null,
    "location": {
      "country": "Germany"
    },
    "totalSpent": 0,
    "totalReviews": 0,
    "totalFeedback": 0,
    "companyRid": 0,
    "companyName": null,
    "edcUserId": 0,
    "lastContractPlatform": null,
    "lastContractRid": 0,
    "lastContractTitle": null,
    "feedbackText": "No feedback yet",
    "companyOrgUid": null,
    "hasFinancialPrivacy": false
  },
  "freelancersToHire": 1,
  "relevanceEncoded": "{\u0022position\u0022:\u002288\u0022}",
  "isSTSVectorSearchResult": false,
  "enterpriseJob": false,
  "tierText": "Expert",
  "tier": "Expert",
  "tierLabel": "Experience Level",
  "isSaved": null,
  "feedback": "",
  "proposalsTier": "50\u002B",
  "isApplied": false,
  "sticky": false,
  "stickyLabel": "",
  "jobTs": "1709581542000",
  "prefFreelancerLocationMandatory": false,
  "prefFreelancerLocation": [],
  "premium": false,
  "plusBadge": null,
  "publishedOn": "2024-03-04T19:45:42\u002B00:00",
  "renewedOn": null,
  "sandsService": null,
  "sandsSpec": null,
  "sandsAttrs": null,
  "occupation": null,
  "attrs": [
    {
      "parentSkillUid": null,
      "freeText": null,
      "skillType": 3,
      "uid": "1031626732825198592",
      "highlighted": true,
      "prettyName": ".NET Framework"
    },
    {
      "parentSkillUid": null,
      "freeText": null,
      "skillType": 3,
      "uid": "1031626716547104768",
      "highlighted": true,
      "prettyName": "ASP.NET MVC"
    },
    {
      "parentSkillUid": null,
      "freeText": null,
      "skillType": 3,
      "uid": "1031626716513550336",
      "highlighted": true,
      "prettyName": "ASP.NET"
    },
    {
      "parentSkillUid": null,
      "freeText": null,
      "skillType": 3,
      "uid": "1110580737240190976",
      "highlighted": false,
      "prettyName": "Web Application"
    },
    {
      "parentSkillUid": null,
      "freeText": null,
      "skillType": 3,
      "uid": "996364628000108549",
      "highlighted": false,
      "prettyName": "SQLite"
    },
    {
      "parentSkillUid": null,
      "freeText": null,
      "skillType": 3,
      "uid": "1031626773660942336",
      "highlighted": false,
      "prettyName": "React"
    },
    {
      "parentSkillUid": null,
      "freeText": null,
      "skillType": 3,
      "uid": "996364628025274383",
      "highlighted": false,
      "prettyName": "JavaScript"
    }
  ],
  "isLocal": false,
  "workType": null,
  "locations": [],
  "occupations": {
    "category": {
      "uid": "531770282580668418",
      "prefLabel": "Web, Mobile \u0026 Software Dev"
    },
    "subcategories": [
      {
        "uid": "531770282584862733",
        "prefLabel": "Web Development"
      }
    ],
    "oservice": {
      "uid": "1110580755107926016",
      "prefLabel": "Full Stack Development"
    }
  },
  "weeklyBudget": {
    "currencyCode": "USD",
    "amount": 0
  },
  "hourlyBudgetText": "$30.00-$60.00",
  "hourlyBudget": {
    "type": "MANUAL",
    "min": 30,
    "max": 60
  },
  "tags": [],
  "clientRelation": null,
  "totalFreelancersToHire": null,
  "teamUid": null,
  "multipleFreelancersToHirePredicted": null,
  "connectPrice": 16
}