{
  "title": "Property Rental Management",
  "createdOn": "2024-03-14T19:35:15\u002B00:00",
  "type": 2,
  "ciphertext": "~0194ee87425f68e16c",
  "description": "We need to integrate an MVC Property |Rental Management app into our existing website.\n\nWe also need to use the Bryntum library of js components such as its Scehduler etc.",
  "category2": null,
  "subcategory2": null,
  "duration": "1 to 3 months",
  "shortDuration": "1-3 months",
  "durationLabel": "1 to 3 months",
  "engagement": "not_sure",
  "shortEngagement": "not_sure",
  "amount": {
    "currencyCode": "USD",
    "amount": 0
  },
  "recno": 1011990810,
  "uid": "1768360260981555200",
  "client": {
    "paymentVerificationStatus": 1,
    "location": {
      "country": "Ireland"
    },
    "totalSpent": 4212,
    "totalReviews": 20,
    "totalFeedback": 4.2549791,
    "companyRid": 0,
    "companyName": null,
    "edcUserId": 0,
    "lastContractPlatform": null,
    "lastContractRid": 0,
    "lastContractTitle": null,
    "feedbackText": "4.25 Stars, based on 20 feedbacks",
    "companyOrgUid": null,
    "hasFinancialPrivacy": false
  },
  "freelancersToHire": 1,
  "relevanceEncoded": "{\u0022position\u0022:\u002258\u0022}",
  "isSTSVectorSearchResult": false,
  "enterpriseJob": false,
  "tierText": "Expert",
  "tier": "Expert",
  "tierLabel": "Experience Level",
  "isSaved": null,
  "feedback": "",
  "proposalsTier": "50\u002B",
  "isApplied": false,
  "sticky": false,
  "stickyLabel": "",
  "jobTs": "1710444915000",
  "prefFreelancerLocationMandatory": false,
  "prefFreelancerLocation": [],
  "premium": false,
  "plusBadge": null,
  "publishedOn": "2024-03-14T19:35:15\u002B00:00",
  "renewedOn": null,
  "sandsService": null,
  "sandsSpec": null,
  "sandsAttrs": null,
  "occupation": null,
  "attrs": [
    {
      "parentSkillUid": null,
      "freeText": null,
      "skillType": 3,
      "uid": "1192876983507763200",
      "highlighted": true,
      "prettyName": ".NET Core"
    },
    {
      "parentSkillUid": null,
      "freeText": null,
      "skillType": 3,
      "uid": "996364628025274380",
      "highlighted": false,
      "prettyName": "C#"
    },
    {
      "parentSkillUid": null,
      "freeText": null,
      "skillType": 3,
      "uid": "996364628025274383",
      "highlighted": false,
      "prettyName": "JavaScript"
    },
    {
      "parentSkillUid": null,
      "freeText": null,
      "skillType": 3,
      "uid": "1484275238163894272",
      "highlighted": false,
      "prettyName": "Property Management"
    }
  ],
  "isLocal": false,
  "workType": null,
  "locations": [],
  "occupations": {
    "category": {
      "uid": "531770282580668418",
      "prefLabel": "Web, Mobile \u0026 Software Dev"
    },
    "subcategories": [
      {
        "uid": "531770282584862733",
        "prefLabel": "Web Development"
      }
    ],
    "oservice": {
      "uid": "1110580755107926016",
      "prefLabel": "Full Stack Development"
    }
  },
  "weeklyBudget": {
    "currencyCode": "USD",
    "amount": 0
  },
  "hourlyBudgetText": "$25.00-$50.00",
  "hourlyBudget": {
    "type": "DEFAULT",
    "min": 25,
    "max": 50
  },
  "tags": [],
  "clientRelation": null,
  "totalFreelancersToHire": null,
  "teamUid": null,
  "multipleFreelancersToHirePredicted": null,
  "connectPrice": 16
}